redis_cached/__init__.py
redis_cached/core.py
redis_cached/utils.py
redis_cached-0.4.5.dist-info/LICENSE
redis_cached-0.4.5.dist-info/METADATA
redis_cached-0.4.5.dist-info/WHEEL
redis_cached-0.4.5.dist-info/RECORD
