Metadata-Version: 2.1
Name: redis-cached
Version: 0.4.5
Summary: Python cache decorator and other itils with support for Redis or KeyDB
Home-page: https://github.com/dmitrybabanovforreal/redis-cached
Author: Dmitry Babanov
Author-email: 85852989+dmitrybabanovforreal@users.noreply.github.com
Requires-Python: >=3.12,<3.14
Classifier: Programming Language :: Python :: 3
Classifier: Programming Language :: Python :: 3.12
Requires-Dist: redis (>=4.5.5,<5.1.0)
